{
  "http://dbpedia.org/resource/Wood_Green_tube_station" : { "http://www.w3.org/1999/02/22-rdf-syntax-ns#type" : [ { "type" : "uri", "value" : "http://schema.org/Place" } ,
      { "type" : "uri", "value" : "http://dbpedia.org/ontology/Station" } ,
      { "type" : "uri", "value" : "http://dbpedia.org/ontology/ArchitecturalStructure" } ,
      { "type" : "uri", "value" : "http://www.w3.org/2002/07/owl#Thing" } ,
      { "type" : "uri", "value" : "http://dbpedia.org/ontology/Place" } ,
      { "type" : "uri", "value" : "http://www.opengis.net/gml/_Feature" } ,
      { "type" : "uri", "value" : "http://dbpedia.org/ontology/Infrastructure" } ] ,
    "http://www.w3.org/2000/01/rdf-schema#label" : [ { "type" : "literal", "value" : "Wood Green tube station" , "lang" : "en" } ] ,
    "http://www.w3.org/2000/01/rdf-schema#comment" : [ { "type" : "literal", "value" : "Wood Green is a London Underground station on the Piccadilly Line. The station is between Turnpike Lane and Bounds Green stations and is in Travelcard Zone 3. It is located at junction of Wood Green High Road and Lordship Lane. It serves Wood Green Shopping City and the nearby Haringey Council administrative complex as well as a densely populated residential area." , "lang" : "en" } ] ,
    "http://www.w3.org/2002/07/owl#sameAs" : [ { "type" : "uri", "value" : "http://rdf.freebase.com/ns/m.03dx9f" } ,
      { "type" : "uri", "value" : "http://dbpedia.org/resource/Wood_Green_tube_station" } ] ,
    "http://www.w3.org/2003/01/geo/wgs84_pos#long" : [ { "type" : "literal", "value" : -0.1099999994039536 , "datatype" : "http://www.w3.org/2001/XMLSchema#float" } ] ,
    "http://purl.org/dc/terms/subject" : [ { "type" : "uri", "value" : "http://dbpedia.org/resource/Category:Railway_stations_opened_in_1932" } ,
      { "type" : "uri", "value" : "http://dbpedia.org/resource/Category:Piccadilly_Line_stations" } ,
      { "type" : "uri", "value" : "http://dbpedia.org/resource/Category:Tube_stations_in_Haringey" } ,
      { "type" : "uri", "value" : "http://dbpedia.org/resource/Category:Charles_Holden_buildings" } ] ,
    "http://dbpedia.org/property/platforms" : [ { "type" : "literal", "value" : 2 , "datatype" : "http://www.w3.org/2001/XMLSchema#integer" } ] ,
    "http://dbpedia.org/property/events" : [ { "type" : "literal", "value" : "Opened" , "lang" : "en" } ] ,
    "http://dbpedia.org/property/previous" : [ { "type" : "literal", "value" : "Turnpike Lane" , "lang" : "en" } ] ,
    "http://dbpedia.org/property/borough" : [ { "type" : "uri", "value" : "http://dbpedia.org/resource/London_Borough_of_Haringey" } ] ,
    "http://dbpedia.org/property/imageName" : [ { "type" : "literal", "value" : "Wood Green tube station 070414.JPG" , "lang" : "en" } ] ,
    "http://dbpedia.org/property/wikiPageUsesTemplate" : [ { "type" : "uri", "value" : "http://dbpedia.org/resource/Template:S-line" } ,
      { "type" : "uri", "value" : "http://dbpedia.org/resource/Template:Infobox_London_station" } ] ,
    "http://www.georss.org/georss/point" : [ { "type" : "literal", "value" : "51.597 -0.11" , "lang" : "en" } ] ,
    "http://dbpedia.org/ontology/wikiPageExternalLink" : [ { "type" : "uri", "value" : "http://photos.ltmcollection.org" } ] ,
    "http://dbpedia.org/property/name" : [ { "type" : "literal", "value" : "Wood Green" , "lang" : "en" } ] ,
    "http://dbpedia.org/ontology/country" : [ { "type" : "uri", "value" : "http://dbpedia.org/resource/United_Kingdom" } ] ,
    "http://dbpedia.org/property/longitude" : [ { "type" : "literal", "value" : 0 , "datatype" : "http://www.w3.org/2001/XMLSchema#integer" } ] ,
    "http://dbpedia.org/ontology/location" : [ { "type" : "uri", "value" : "http://dbpedia.org/resource/Wood_Green" } ,
      { "type" : "uri", "value" : "http://dbpedia.org/resource/London_Borough_of_Haringey" } ,
      { "type" : "uri", "value" : "http://dbpedia.org/resource/Greater_London" } ] ,
    "http://dbpedia.org/property/years" : [ { "type" : "literal", "value" : 1932 , "datatype" : "http://www.w3.org/2001/XMLSchema#integer" } ] ,
    "http://dbpedia.org/property/locale" : [ { "type" : "uri", "value" : "http://dbpedia.org/resource/Wood_Green" } ] ,
    "http://dbpedia.org/ontology/district" : [ { "type" : "uri", "value" : "http://dbpedia.org/resource/London_Borough_of_Haringey" } ] ,
    "http://dbpedia.org/property/symbol" : [ { "type" : "literal", "value" : "underground" , "lang" : "en" } ] ,
    "http://www.w3.org/2003/01/geo/wgs84_pos#lat" : [ { "type" : "literal", "value" : 51.59700012207031 , "datatype" : "http://www.w3.org/2001/XMLSchema#float" } ] ,
    "http://xmlns.com/foaf/0.1/name" : [ { "type" : "literal", "value" : "Wood Green" , "lang" : "en" } ] ,
    "http://dbpedia.org/property/latitude" : [ { "type" : "literal", "value" : 52 , "datatype" : "http://www.w3.org/2001/XMLSchema#integer" } ] ,
    "http://dbpedia.org/property/manager" : [ { "type" : "uri", "value" : "http://dbpedia.org/resource/London_Underground" } ] ,
    "http://dbpedia.org/property/next" : [ { "type" : "literal", "value" : "Bounds Green" , "lang" : "en" } ] ,
    "http://dbpedia.org/property/line" : [ { "type" : "literal", "value" : "Piccadilly" , "lang" : "en" } ] ,
    "http://dbpedia.org/property/system" : [ { "type" : "literal", "value" : "LUL" , "lang" : "en" } ] ,
    "http://dbpedia.org/ontology/thumbnail" : [ { "type" : "uri", "value" : "http://upload.wikimedia.org/wikipedia/commons/thumb/3/36/Wood_Green_tube_station_070414.JPG/200px-Wood_Green_tube_station_070414.JPG" } ] ,
    "http://dbpedia.org/ontology/railwayPlatforms" : [ { "type" : "literal", "value" : "2 wood Green Train Station" , "lang" : "en" } ] ,
    "http://dbpedia.org/property/fareZone" : [ { "type" : "literal", "value" : 3 , "datatype" : "http://www.w3.org/2001/XMLSchema#integer" } ] ,
    "http://dbpedia.org/property/tubeexits" : [ { "type" : "literal", "value" : 11 , "datatype" : "http://www.w3.org/2001/XMLSchema#integer" } ] ,
    "http://dbpedia.org/ontology/abstract" : [ { "type" : "literal", "value" : "Wood Green is a London Underground station on the Piccadilly Line. The station is between Turnpike Lane and Bounds Green stations and is in Travelcard Zone 3. It is located at junction of Wood Green High Road and Lordship Lane. It serves Wood Green Shopping City and the nearby Haringey Council administrative complex as well as a densely populated residential area." , "lang" : "en" } ] ,
    "http://dbpedia.org/ontology/fareZone" : [ { "type" : "literal", "value" : "3" , "lang" : "en" } ] ,
    "http://dbpedia.org/ontology/operatedBy" : [ { "type" : "uri", "value" : "http://dbpedia.org/resource/London_Underground" } ] ,
    "http://dbpedia.org/property/hasPhotoCollection" : [ { "type" : "uri", "value" : "http://www4.wiwiss.fu-berlin.de/flickrwrappr/photos/Wood_Green_tube_station" } ] ,
    "http://dbpedia.org/property/wordnet_type" : [ { "type" : "uri", "value" : "http://www.w3.org/2006/03/wn/wn20/instances/synset-railway_station-noun-1" } ] ,
    "http://xmlns.com/foaf/0.1/depiction" : [ { "type" : "uri", "value" : "http://upload.wikimedia.org/wikipedia/commons/3/36/Wood_Green_tube_station_070414.JPG" } ] ,
    "http://xmlns.com/foaf/0.1/isPrimaryTopicOf" : [ { "type" : "uri", "value" : "http://en.wikipedia.org/wiki/Wood_Green_tube_station" } ] } ,
  "http://dbpedia.org/resource/London_Buses_route_230" : { "http://dbpedia.org/property/start" : [ { "type" : "uri", "value" : "http://dbpedia.org/resource/Wood_Green_tube_station" } ] } ,
  "http://dbpedia.org/resource/Wood_green_station" : { "http://dbpedia.org/ontology/wikiPageRedirects" : [ { "type" : "uri", "value" : "http://dbpedia.org/resource/Wood_Green_tube_station" } ] } ,
  "http://dbpedia.org/resource/Wood_Green_Underground_station" : { "http://dbpedia.org/ontology/wikiPageRedirects" : [ { "type" : "uri", "value" : "http://dbpedia.org/resource/Wood_Green_tube_station" } ] } ,
  "http://en.wikipedia.org/wiki/Wood_Green_tube_station" : { "http://xmlns.com/foaf/0.1/primaryTopic" : [ { "type" : "uri", "value" : "http://dbpedia.org/resource/Wood_Green_tube_station" } ] }
}
