{
  "http://en.wikipedia.org/wiki/North_Harrow_tube_station" : { "http://xmlns.com/foaf/0.1/primaryTopic" : [ { "type" : "uri", "value" : "http://dbpedia.org/resource/North_Harrow_tube_station" } ] } ,
  "http://dbpedia.org/resource/North_Harrow_tube_station" : { "http://www.w3.org/1999/02/22-rdf-syntax-ns#type" : [ { "type" : "uri", "value" : "http://dbpedia.org/ontology/Station" } ,
      { "type" : "uri", "value" : "http://www.w3.org/2002/07/owl#Thing" } ,
      { "type" : "uri", "value" : "http://schema.org/Place" } ,
      { "type" : "uri", "value" : "http://dbpedia.org/ontology/ArchitecturalStructure" } ,
      { "type" : "uri", "value" : "http://dbpedia.org/ontology/Place" } ,
      { "type" : "uri", "value" : "http://dbpedia.org/ontology/Infrastructure" } ] ,
    "http://www.w3.org/2002/07/owl#sameAs" : [ { "type" : "uri", "value" : "http://dbpedia.org/resource/North_Harrow_tube_station" } ,
      { "type" : "uri", "value" : "http://rdf.freebase.com/ns/m.04gn3g" } ,
      { "type" : "uri", "value" : "http://fr.dbpedia.org/resource/North_Harrow_(m\u00E9tro_de_Londres)" } ,
      { "type" : "uri", "value" : "http://de.dbpedia.org/resource/North_Harrow_(London_Underground)" } ,
      { "type" : "uri", "value" : "http://ru.dbpedia.org/resource/\u0421\u0435\u0432\u0435\u0440\u043D\u044B\u0439_\u0425\u0430\u0440\u0440\u043E\u0443_(\u0441\u0442\u0430\u043D\u0446\u0438\u044F_\u043C\u0435\u0442\u0440\u043E)" } ] ,
    "http://purl.org/dc/terms/subject" : [ { "type" : "uri", "value" : "http://dbpedia.org/resource/Category:Former_Metropolitan_and_Great_Central_Joint_Railway_stations" } ,
      { "type" : "uri", "value" : "http://dbpedia.org/resource/Category:Tube_stations_in_Harrow" } ,
      { "type" : "uri", "value" : "http://dbpedia.org/resource/Category:Railway_stations_opened_in_1915" } ,
      { "type" : "uri", "value" : "http://dbpedia.org/resource/Category:Metropolitan_Line_stations" } ] ,
    "http://www.w3.org/2000/01/rdf-schema#label" : [ { "type" : "literal", "value" : "North Harrow tube station" , "lang" : "en" } ,
      { "type" : "literal", "value" : "North Harrow (London Underground)" , "lang" : "de" } ] ,
    "http://xmlns.com/foaf/0.1/depiction" : [ { "type" : "uri", "value" : "http://upload.wikimedia.org/wikipedia/commons/8/8e/N_Harrow_station.jpg" } ] ,
    "http://www.w3.org/2000/01/rdf-schema#comment" : [ { "type" : "literal", "value" : "North Harrow is een station van de metro van Londen aan de Metropolitan Line. Het metrostation, dat in 1915 is geopend, ligt in de wijk Harrow." , "lang" : "nl" } ,
      { "type" : "literal", "value" : "North Harrow ist eine oberirdische Station der London Underground im Stadtbezirk London Borough of Harrow. Sie liegt in der Travelcard- Tarifzone 5 an der Station Road. Die von der Metropolitan Line bediente Station wurde im Jahr 2007 von 1,432 Millionen Fahrg\u00E4sten genutzt. Die Station liegt am viergleisigen Streckenabschnitt zwischen Harrow-on-the-Hill und Moor Park. Nur die beiden n\u00F6rdlichen Gleise verf\u00FCgen \u00FCber Seitenbahnsteige, an diesen halten Lokalz\u00FCge der Metropolitan Line." , "lang" : "de" } ,
      { "type" : "literal", "value" : "\u00AB\u0421\u0435\u0432\u0435\u0440\u043D\u044B\u0439 \u0425\u0430\u0440\u0440\u043E\u0443\u00BB\u00A0\u2014 \u0441\u0442\u0430\u043D\u0446\u0438\u044F \u043B\u043E\u043D\u0434\u043E\u043D\u0441\u043A\u043E\u0433\u043E \u043C\u0435\u0442\u0440\u043E. \u0421\u0442\u0430\u043D\u0446\u0438\u044F \u043E\u0442\u043D\u043E\u0441\u0438\u0442\u0441\u044F \u043A 5 \u0442\u0440\u0430\u043D\u0441\u043F\u043E\u0440\u0442\u043D\u043E\u0439 \u0437\u043E\u043D\u0435 \u0438 \u043E\u0431\u0441\u043B\u0443\u0436\u0438\u0432\u0430\u0435\u0442\u0441\u044F \u043F\u043E\u0435\u0437\u0434\u0430\u043C\u0438 \u043B\u0438\u043D\u0438\u0438 \u041C\u0435\u0442\u0440\u043E\u043F\u043E\u043B\u0438\u0442\u044D\u043D." , "lang" : "ru" } ,
      { "type" : "literal", "value" : "North Harrow underground station is a London Underground station situated in North Harrow, North West London. The station is on the Metropolitan Line and is the station between Harrow-on-the-Hill (southbound) and Pinner (northbound). Fast Metropolitan Line and Chiltern Railways services pass by using two of the four tracks. It has won transport for London awards for best customer service in 2009 and 2010." , "lang" : "en" } ,
      { "type" : "literal", "value" : "North Harrow est une station du m\u00E9tro de Londres." , "lang" : "fr" } ] ,
    "http://xmlns.com/foaf/0.1/name" : [ { "type" : "literal", "value" : "North Harrow" , "lang" : "en" } ] ,
    "http://dbpedia.org/ontology/fareZone" : [ { "type" : "literal", "value" : "5" , "lang" : "en" } ] ,
    "http://dbpedia.org/ontology/operatedBy" : [ { "type" : "uri", "value" : "http://dbpedia.org/resource/London_Underground" } ] ,
    "http://dbpedia.org/ontology/railwayPlatforms" : [ { "type" : "literal", "value" : "2" , "lang" : "en" } ] ,
    "http://xmlns.com/foaf/0.1/isPrimaryTopicOf" : [ { "type" : "uri", "value" : "http://en.wikipedia.org/wiki/North_Harrow_tube_station" } ] ,
    "http://dbpedia.org/property/tubeexits" : [ { "type" : "literal", "value" : "1" , "datatype" : "http://www.w3.org/2001/XMLSchema#int" } ] ,
    "http://www.w3.org/ns/prov#wasDerivedFrom" : [ { "type" : "uri", "value" : "http://en.wikipedia.org/wiki/North_Harrow_tube_station?oldid=489312155" } ] ,
    "http://dbpedia.org/property/manager" : [ { "type" : "uri", "value" : "http://dbpedia.org/resource/London_Underground" } ] ,
    "http://dbpedia.org/ontology/abstract" : [ { "type" : "literal", "value" : "North Harrow underground station is a London Underground station situated in North Harrow, North West London. The station is on the Metropolitan Line and is the station between Harrow-on-the-Hill (southbound) and Pinner (northbound). Fast Metropolitan Line and Chiltern Railways services pass by using two of the four tracks. It has won transport for London awards for best customer service in 2009 and 2010. To travel to the station via Harrow-on-the-Hill northbound, one must take an all stations or semi-fast Metropolitan Line train, or slow Amersham train. The steps to the station exit are towards the rear of the train when heading northbound, or front when heading southbound. The Metropolitan Railway began running services through here on 25 May 1885 with the opening of its Pinner extension. North Harrow station opened on 22 March 1915. The station was rebuilt in 1930 to the designs of Charles Clark as part of the Metropolitan Railway's modernisation programme Currently the art on display are photocopied pictures of local people painted over with coloured paint in various places, made by a local disabled children's group. It has two main exits but in recent years only one is in use, towards the town centre, presumably due to the setup of the barriers not requiring both. There is a direct door into a neighbouring coffee shop. The area under the train bridge outside the exit to the station is prone to flooding at times due to its low-lying position." , "lang" : "en" } ,
      { "type" : "literal", "value" : "\u00AB\u0421\u0435\u0432\u0435\u0440\u043D\u044B\u0439 \u0425\u0430\u0440\u0440\u043E\u0443\u00BB\u00A0\u2014 \u0441\u0442\u0430\u043D\u0446\u0438\u044F \u043B\u043E\u043D\u0434\u043E\u043D\u0441\u043A\u043E\u0433\u043E \u043C\u0435\u0442\u0440\u043E. \u0421\u0442\u0430\u043D\u0446\u0438\u044F \u043E\u0442\u043D\u043E\u0441\u0438\u0442\u0441\u044F \u043A 5 \u0442\u0440\u0430\u043D\u0441\u043F\u043E\u0440\u0442\u043D\u043E\u0439 \u0437\u043E\u043D\u0435 \u0438 \u043E\u0431\u0441\u043B\u0443\u0436\u0438\u0432\u0430\u0435\u0442\u0441\u044F \u043F\u043E\u0435\u0437\u0434\u0430\u043C\u0438 \u043B\u0438\u043D\u0438\u0438 \u041C\u0435\u0442\u0440\u043E\u043F\u043E\u043B\u0438\u0442\u044D\u043D." , "lang" : "ru" } ,
      { "type" : "literal", "value" : "North Harrow ist eine oberirdische Station der London Underground im Stadtbezirk London Borough of Harrow. Sie liegt in der Travelcard- Tarifzone 5 an der Station Road. Die von der Metropolitan Line bediente Station wurde im Jahr 2007 von 1,432 Millionen Fahrg\u00E4sten genutzt. Die Station liegt am viergleisigen Streckenabschnitt zwischen Harrow-on-the-Hill und Moor Park. Nur die beiden n\u00F6rdlichen Gleise verf\u00FCgen \u00FCber Seitenbahnsteige, an diesen halten Lokalz\u00FCge der Metropolitan Line. Expressz\u00FCge der Metropolitan Line sowie s\u00E4mtliche Z\u00FCge der Bahngesellschaft Chiltern Railways fahren auf den beiden s\u00FCdlichen Gleisen ohne Halt durch. Die Strecke der Metropolitan Railway (Vorg\u00E4ngergesellschaft der Metropolitan Line) bestand zwar bereits seit dem 25. Mai 1885, doch die Station wurde erst nachtr\u00E4glich gebaut, da die Dichte der Bebauung zu Beginn noch sehr gering war. Die Er\u00F6ffnung erfolgte am 22. M\u00E4rz 1915. Am 5. Januar 1925 wurde der Abschnitt Harrow-on-the-Hill \u2013 Rickmansworth elektrifiziert. Im Jahr 1961 erhielt die Strecke zwischen Harrow-on-the-Hill und Northwood Hills eine zweite Doppelspur." , "lang" : "de" } ,
      { "type" : "literal", "value" : "North Harrow is een station van de metro van Londen aan de Metropolitan Line. Het metrostation, dat in 1915 is geopend, ligt in de wijk Harrow." , "lang" : "nl" } ,
      { "type" : "literal", "value" : "North Harrow est une station du m\u00E9tro de Londres." , "lang" : "fr" } ] ,
    "http://dbpedia.org/ontology/location" : [ { "type" : "uri", "value" : "http://dbpedia.org/resource/Greater_London" } ,
      { "type" : "uri", "value" : "http://dbpedia.org/resource/Harrow,_London" } ,
      { "type" : "uri", "value" : "http://dbpedia.org/resource/London_Borough_of_Harrow" } ] ,
    "http://dbpedia.org/ontology/thumbnail" : [ { "type" : "uri", "value" : "http://upload.wikimedia.org/wikipedia/commons/thumb/8/8e/N_Harrow_station.jpg/200px-N_Harrow_station.jpg" } ] ,
    "http://dbpedia.org/property/name" : [ { "type" : "literal", "value" : "North Harrow" , "lang" : "en" } ] ,
    "http://dbpedia.org/property/next" : [ { "type" : "literal", "value" : "Harrow-on-the-Hill" , "lang" : "en" } ] ,
    "http://dbpedia.org/property/years" : [ { "type" : "literal", "value" : "25" , "datatype" : "http://www.w3.org/2001/XMLSchema#int" } ,
      { "type" : "literal", "value" : "22" , "datatype" : "http://www.w3.org/2001/XMLSchema#int" } ] ,
    "http://dbpedia.org/property/wordnet_type" : [ { "type" : "uri", "value" : "http://www.w3.org/2006/03/wn/wn20/instances/synset-railway_station-noun-1" } ] ,
    "http://dbpedia.org/property/wikiPageUsesTemplate" : [ { "type" : "uri", "value" : "http://dbpedia.org/resource/Template:Infobox_London_station" } ,
      { "type" : "uri", "value" : "http://dbpedia.org/resource/Template:S-line" } ] ,
    "http://dbpedia.org/property/hasPhotoCollection" : [ { "type" : "uri", "value" : "http://www4.wiwiss.fu-berlin.de/flickrwrappr/photos/North_Harrow_tube_station" } ] ,
    "http://dbpedia.org/ontology/country" : [ { "type" : "uri", "value" : "http://dbpedia.org/resource/United_Kingdom" } ] ,
    "http://dbpedia.org/ontology/district" : [ { "type" : "uri", "value" : "http://dbpedia.org/resource/London_Borough_of_Harrow" } ] ,
    "http://dbpedia.org/property/borough" : [ { "type" : "uri", "value" : "http://dbpedia.org/resource/London_Borough_of_Harrow" } ] ,
    "http://dbpedia.org/property/fareZone" : [ { "type" : "literal", "value" : "5" , "datatype" : "http://www.w3.org/2001/XMLSchema#int" } ] ,
    "http://dbpedia.org/property/type" : [ { "type" : "literal", "value" : "Three" , "lang" : "en" } ] ,
    "http://dbpedia.org/property/events" : [ { "type" : "literal", "value" : "Line opened" , "lang" : "en" } ,
      { "type" : "literal", "value" : "Station opened" , "lang" : "en" } ] ,
    "http://dbpedia.org/property/system" : [ { "type" : "literal", "value" : "LUL" , "lang" : "en" } ] ,
    "http://dbpedia.org/property/imageName" : [ { "type" : "literal", "value" : "N Harrow station.jpg" , "lang" : "en" } ] ,
    "http://dbpedia.org/property/locale" : [ { "type" : "uri", "value" : "http://dbpedia.org/resource/Harrow,_London" } ] ,
    "http://dbpedia.org/property/original" : [ { "type" : "uri", "value" : "http://dbpedia.org/resource/Metropolitan_and_Great_Central_Joint_Railway" } ] ,
    "http://dbpedia.org/property/postgroup" : [ { "type" : "literal", "value" : "Metropolitan and Great Central Joint Railway" , "lang" : "en" } ] ,
    "http://dbpedia.org/property/pregroup" : [ { "type" : "literal", "value" : "Metropolitan and Great Central Joint Railway" , "lang" : "en" } ] ,
    "http://dbpedia.org/property/symbol" : [ { "type" : "literal", "value" : "underground" , "lang" : "en" } ] ,
    "http://dbpedia.org/property/platforms" : [ { "type" : "literal", "value" : "2" , "datatype" : "http://www.w3.org/2001/XMLSchema#int" } ] ,
    "http://dbpedia.org/property/previous" : [ { "type" : "literal", "value" : "Pinner" , "lang" : "en" } ] ,
    "http://dbpedia.org/property/line" : [ { "type" : "literal", "value" : "Metropolitan" , "lang" : "en" } ] ,
    "http://dbpedia.org/property/tubecode" : [ { "type" : "literal", "value" : "ZNH" , "lang" : "en" } ] } ,
  "http://dbpedia.org/resource/North_Harrow_Underground_station" : { "http://dbpedia.org/ontology/wikiPageRedirects" : [ { "type" : "uri", "value" : "http://dbpedia.org/resource/North_Harrow_tube_station" } ] } ,
  "http://dbpedia.org/resource/North_Harrow_railway_station" : { "http://dbpedia.org/ontology/wikiPageRedirects" : [ { "type" : "uri", "value" : "http://dbpedia.org/resource/North_Harrow_tube_station" } ] } ,
  "http://dbpedia.org/resource/North_Harrow_station" : { "http://dbpedia.org/ontology/wikiPageRedirects" : [ { "type" : "uri", "value" : "http://dbpedia.org/resource/North_Harrow_tube_station" } ] } ,
  "http://dbpedia.org/resource/North_harrow_tube_station" : { "http://dbpedia.org/ontology/wikiPageRedirects" : [ { "type" : "uri", "value" : "http://dbpedia.org/resource/North_Harrow_tube_station" } ] } ,
  "http://dbpedia.org/resource/Harrow_tube_station" : { "http://dbpedia.org/ontology/wikiPageDisambiguates" : [ { "type" : "uri", "value" : "http://dbpedia.org/resource/North_Harrow_tube_station" } ] }
}
